osrsbox/__init__.py
osrsbox/docs/items-complete.json
osrsbox/docs/monsters-complete.json
osrsbox/docs/prayers-complete.json
osrsbox/items_api/__init__.py
osrsbox/items_api/all_items.py
osrsbox/items_api/item_equipment.py
osrsbox/items_api/item_properties.py
osrsbox/items_api/item_weapon.py
osrsbox/items_api_examples/generate_chunktracker_data.py
osrsbox/items_api_examples/generate_invalid_items.py
osrsbox/items_api_examples/guess_the_item_game.py
osrsbox/items_api_examples/items_to_csv.py
osrsbox/items_api_examples/lookup_methods_examples.py
osrsbox/items_api_examples/print_all_items.py
osrsbox/items_api_examples/print_f2p_weapons.py
osrsbox/items_api_examples/print_highest_prayer_items.py
osrsbox/items_api_examples/print_highest_slash_bonus.py
osrsbox/items_api_examples/print_sort_item_releases.py
osrsbox/monsters_api/__init__.py
osrsbox/monsters_api/all_monsters.py
osrsbox/monsters_api/monster_drop.py
osrsbox/monsters_api/monster_properties.py
osrsbox/monsters_api_examples/find_rarest_drops.py
osrsbox/monsters_api_examples/print_all_monsters.py
osrsbox/monsters_api_examples/print_slayer_tasks.py
osrsbox/monsters_api_examples/search_monster_drops.py
osrsbox/monsters_api_examples/test_drops_rarity.py
osrsbox/prayers_api/__init__.py
osrsbox/prayers_api/all_prayers.py
osrsbox/prayers_api/prayer_properties.py
osrsbox-2.2.2.dist-info/LICENSE
osrsbox-2.2.2.dist-info/WHEEL
osrsbox-2.2.2.dist-info/METADATA
osrsbox-2.2.2.dist-info/RECORD
