Metadata-Version: 2.1
Name: osrsbox
Version: 2.2.2
Summary: A complete and up-to-date database of Old School Runescape (OSRS) items, monsters and prayers accessible using a Python API.
Home-page: https://github.com/osrsbox/osrsbox-db
License: GPL-3.0-only
Author: PH01L
Author-email: phoil@osrsbox.com
Requires-Python: >=3.6,<4.0
Classifier: License :: OSI Approved :: GNU General Public License v3 (GPLv3)
Classifier: Programming Language :: Python :: 3
Classifier: Programming Language :: Python :: 3.6
Classifier: Programming Language :: Python :: 3.7
Classifier: Programming Language :: Python :: 3.8
Classifier: Programming Language :: Python :: 3.9
Requires-Dist: dataclasses
Project-URL: Repository, https://github.com/osrsbox/osrsbox-db
